deeplynx_provider/__init__.py
deeplynx_provider/example_dags/__init__.py
deeplynx_provider/example_dags/data_query.py
deeplynx_provider/example_dags/data_query_then_parse.py
deeplynx_provider/example_dags/deeplynx_config_upload_download.py
deeplynx_provider/example_dags/deeplynx_provider_test.py
deeplynx_provider/example_dags/get_token_with_key_secret.py
deeplynx_provider/example_dags/trigger_get_token_with_post.py
deeplynx_provider/example_dags/upload_files.py
deeplynx_provider/hooks/__init__.py
deeplynx_provider/hooks/deeplynx.py
deeplynx_provider/operators/__init__.py
deeplynx_provider/operators/attach_node_file_operator.py
deeplynx_provider/operators/configuration_operator.py
deeplynx_provider/operators/create_container_operator.py
deeplynx_provider/operators/create_manual_import_from_path_operator.py
deeplynx_provider/operators/create_manual_import_operator.py
deeplynx_provider/operators/data_query_operator.py
deeplynx_provider/operators/data_query_with_params_operator.py
deeplynx_provider/operators/deeplynx_base_operator.py
deeplynx_provider/operators/download_file_operator.py
deeplynx_provider/operators/get_token_operator.py
deeplynx_provider/operators/import_container_operator.py
deeplynx_provider/operators/metatype_query_operator.py
deeplynx_provider/operators/query_helpers.py
deeplynx_provider/operators/set_data_source_active_operator.py
deeplynx_provider/operators/set_type_mapping_active_operator.py
deeplynx_provider/operators/timeseries_query_all_operator.py
deeplynx_provider/operators/timeseries_query_operator.py
deeplynx_provider/operators/upload_file_operator.py
deeplynx_provider/operators/utils.py
airflow_provider_deeplynx-0.4.7.dist-info/LICENSE
airflow_provider_deeplynx-0.4.7.dist-info/METADATA
airflow_provider_deeplynx-0.4.7.dist-info/WHEEL
airflow_provider_deeplynx-0.4.7.dist-info/entry_points.txt
airflow_provider_deeplynx-0.4.7.dist-info/top_level.txt
airflow_provider_deeplynx-0.4.7.dist-info/RECORD
