Metadata-Version: 2.1
Name: airflow-provider-deeplynx
Version: 0.4.7
Summary: An Apache Airflow provider package built for DeepLynx.
Author-email: Jack Cavaluzzi <jack.cavaluzzi@inl.gov>
License: Apache License 2.0
Project-URL: Source, https://github.com/idaholab/airflow-provider-deeplynx
Classifier: Framework :: Apache Airflow
Classifier: Framework :: Apache Airflow :: Provider
Requires-Python: ~=3.8
License-File: LICENSE
Requires-Dist: apache-airflow>=2.4
Requires-Dist: deep-lynx==0.1.8
